spyder_line_profiler/__init__.py
spyder_line_profiler/example/__init__.py
spyder_line_profiler/example/profiling_test_script.py
spyder_line_profiler/example/subdir/__init__.py
spyder_line_profiler/example/subdir/profiling_test_script2.py
spyder_line_profiler/spyder/__init__.py
spyder_line_profiler/spyder/config.py
spyder_line_profiler/spyder/confpage.py
spyder_line_profiler/spyder/plugin.py
spyder_line_profiler/spyder/run_conf.py
spyder_line_profiler/spyder/widgets.py
spyder_line_profiler/tests/__init__.py
spyder_line_profiler/tests/test_lineprofiler.py
spyder_line_profiler-0.4.2.dist-info/AUTHORS.md
spyder_line_profiler-0.4.2.dist-info/LICENSE.txt
spyder_line_profiler-0.4.2.dist-info/METADATA
spyder_line_profiler-0.4.2.dist-info/WHEEL
spyder_line_profiler-0.4.2.dist-info/entry_points.txt
spyder_line_profiler-0.4.2.dist-info/top_level.txt
spyder_line_profiler-0.4.2.dist-info/RECORD
