Metadata-Version: 2.1
Name: spyder_line_profiler
Version: 0.4.2
Summary: Plugin for the Spyder IDE that integrates the Python line profiler.
Home-page: https://github.com/spyder-ide/spyder-line-profiler
Author: Spyder Project Contributors
License: MIT
Keywords: Qt PyQt5 PySide2 spyder plugins spyplugins line_profiler profiler
Classifier: Development Status :: 4 - Beta
Classifier: Environment :: X11 Applications :: Qt
Classifier: Environment :: Win32 (MS Windows)
Classifier: Intended Audience :: Developers
Classifier: License :: OSI Approved :: MIT License
Classifier: Operating System :: OS Independent
Classifier: Programming Language :: Python :: 3
Classifier: Programming Language :: Python :: 3.10
Classifier: Programming Language :: Python :: 3.11
Classifier: Programming Language :: Python :: 3.12
Classifier: Topic :: Software Development
Classifier: Topic :: Text Editors :: Integrated Development Environments (IDE)
Requires-Python: >= 3.10
License-File: LICENSE.txt
License-File: AUTHORS.md
Requires-Dist: line-profiler
Requires-Dist: qtawesome
Requires-Dist: spyder <6.2,>=6.1
